flask_otpauth.py
setup.py
Flask_OtpAuth.egg-info/PKG-INFO
Flask_OtpAuth.egg-info/SOURCES.txt
Flask_OtpAuth.egg-info/dependency_links.txt
Flask_OtpAuth.egg-info/not-zip-safe
Flask_OtpAuth.egg-info/requires.txt
Flask_OtpAuth.egg-info/top_level.txt