Metadata-Version: 1.0
Name: Flask-OtpAuth
Version: 0.0.1
Summary: One Time Password Authentication for Flask
Home-page: https://github.com/marksteve/flask-otpauth
Author: Mark Steve Samson
Author-email: hello@marksteve.com
License: MIT
Platform: UNKNOWN
